Design Files (*.v)/full_adder.v
module full_adder(a,b,c,s,k);
	input a,b,c;
	output s,k;
	assign s = (a^b)^c;
	assign k = (a&b)|((a^b)&c);
endmodule

Testbenches/tb_full_adder.v
module tb_full_adder();
	reg a,b,c;
	wire s,k;
	full_adder dut (
		.a(a),
		.b(b),
		.c(c),
		.s(s),
		.k(k)
	);
	initial begin
		$dumpfile("full_adder_waveform.vcd");
		$dumpvars(0,tb_full_adder);
		a = 0; b = 0; c = 0;
		#10;
		a = 1; b = 0; c = 0;
		#10;
		a = 0; b = 1; c = 0;
		#10;
		a = 1; b = 1; c = 0;
		#10;
		a = 0; b = 0; c = 1;
		#10;
		a = 1; b = 0; c = 1;
		#10;
		a = 0; b = 1; c = 1;
		#10;
		a = 1; b = 1; c = 1;
		#10;
		$finish;
	end
endmodule

Waveforms/full_adder_waveform.vcd
$date
	Mon Jun  1 17:30:42 2026
$end
$version
	Icarus Verilog
$end
$timescale
	1s
$end
$scope module tb_full_adder $end
$var wire 1 ! s $end
$var wire 1 " k $end
$var reg 1 # a $end
$var reg 1 $ b $end
$var reg 1 % c $end
$scope module dut $end
$var wire 1 # a $end
$var wire 1 $ b $end
$var wire 1 % c $end
$var wire 1 " k $end
$var wire 1 ! s $end
$upscope $end
$upscope $end
$enddefinitions $end
#0
$dumpvars
0%
0$
0#
0"
0!
$end
#10
1!
1#
#20
1$
0#
#30
0!
1"
1#
#40
0"
1!
1%
0$
0#
#50
1"
0!
1#
#60
1$
0#
#70
1!
1#
