Design Files (*.v)/full_subtractor.v
module full_subtractor(a,b,c,diff,borrow);
	input a,b,c;
	output diff,borrow;
	assign diff = (a^b)^c;
	assign borrow = (a&~(b^c))|(~b&c);
endmodule

Testbenches/tb_full_subtractor.v
module tb_full_subtractor();
	reg a,b,c;
	wire diff,borrow;
	full_subtractor dut (
		.a(a),
		.b(b),
		.c(c),
		.diff(diff),
		.borrow(borrow)
	);
	initial begin
		$dumpfile("full_subtractor.vcd");
		$dumpvars(0,tb_full_subtractor);
		a=0;b=0;c=0;#10;
		a=1;b=0;c=0;#10;
		a=0;b=1;c=0;#10;
		a=1;b=1;c=0;#10;
		a=0;b=0;c=1;#10;
		a=1;b=0;c=1;#10;
		a=0;b=1;c=1;#10;
		a=1;b=1;c=1;#10;
		$finish;
	end
endmodule

Waveforms/full_subtractor.vcd
$date
	Tue Jun  2 10:32:28 2026
$end
$version
	Icarus Verilog
$end
$timescale
	1s
$end
$scope module tb_full_subtractor $end
$var wire 1 ! diff $end
$var wire 1 " borrow $end
$var reg 1 # a $end
$var reg 1 $ b $end
$var reg 1 % c $end
$scope module dut $end
$var wire 1 # a $end
$var wire 1 $ b $end
$var wire 1 " borrow $end
$var wire 1 % c $end
$var wire 1 ! diff $end
$upscope $end
$upscope $end
$enddefinitions $end
#0
$dumpvars
0%
0$
0#
0"
0!
$end
#10
1!
1"
1#
#20
0"
1$
0#
#30
0!
1#
#40
1"
1!
1%
0$
0#
#50
0!
1#
#60
0"
1$
0#
#70
1!
1"
1#
